GPTagger/.DS_Store
GPTagger/__init__.py
GPTagger/app.py
GPTagger/constants.py
GPTagger/indexer.py
GPTagger/logger.py
GPTagger/pipelines/__init__.py
GPTagger/pipelines/ner.py
GPTagger/prompt.py
GPTagger/textractor.py
GPTagger/validators/__init__.py
GPTagger/validators/base.py
GPTagger/validators/gpt.py
GPTagger/validators/length.py
GPTagger/validators/regex.py
gptagger-0.0.2.dist-info/LICENSE
gptagger-0.0.2.dist-info/METADATA
gptagger-0.0.2.dist-info/WHEEL
gptagger-0.0.2.dist-info/RECORD
