Metadata-Version: 2.1
Name: gptagger
Version: 0.0.2
Summary: General Purpose Tagger using GPT
Author: Haonan Liu
Author-email: haonan.liu.edu@gmail.com
Requires-Python: >=3.8.1,<4.0.0
Classifier: Programming Language :: Python :: 3
Classifier: Programming Language :: Python :: 3.9
Classifier: Programming Language :: Python :: 3.10
Classifier: Programming Language :: Python :: 3.11
Requires-Dist: fuzzywuzzy (>=0.18.0,<0.19.0)
Requires-Dist: gradio (>=3.38.0,<4.0.0)
Requires-Dist: jinja2 (>=3.1.2,<4.0.0)
Requires-Dist: langchain (>=0.0.222,<0.0.223)
Requires-Dist: openai (>=0.27.8,<0.28.0)
Requires-Dist: python-levenshtein (>=0.21.1,<0.22.0)
Requires-Dist: tiktoken (>=0.4.0,<0.5.0)
Requires-Dist: tqdm (>=4.65.0,<5.0.0)
Requires-Dist: wasabi (>=1.1.2,<2.0.0)
